email_connector/__init__.py
email_connector-0.0.1.dist-info/LICENSE
email_connector-0.0.1.dist-info/METADATA
email_connector-0.0.1.dist-info/WHEEL
email_connector-0.0.1.dist-info/top_level.txt
email_connector-0.0.1.dist-info/RECORD
