Metadata-Version: 2.1
Name: email-connector
Version: 0.0.1
Summary: A small example package
Home-page: UNKNOWN
Author: Margo
Author-email: 935929075@qq.com
License: MIT
Platform: UNKNOWN
Classifier: Programming Language :: Python :: 3
Classifier: License :: OSI Approved :: MIT License
Classifier: Operating System :: OS Independent
Requires-Python: >=3.6
Requires-Dist: yamail (>=1.0.2)
Requires-Dist: imbox (>=0.9.8)
